[null,{"name":"NewEvent","temp":"","event-type":"1","actions":[{"channel":"4","varName":"","message":"*piiiiip*","storage":"0","varName2":"","name":"Send Message"},{"time":"2","measurement":"1","name":"Wait"},{"channel":"4","varName":"","message":"*pooop*","storage":"0","varName2":"","name":"Send Message"},{"time":"1","measurement":"1","name":"Wait"},{"channel":"4","varName":"","message":"*biii*","storage":"0","varName2":"","name":"Send Message"},{"time":"2","measurement":"1","name":"Wait"},{"channel":"4","varName":"","message":"PROCES URUCHOMIENIA ZAKOŃCZONY POMYŚLNIE\n\n\nhlep inc.","storage":"0","varName2":"","name":"Send Message"},{"url":"https://www.google.pl/url?sa=i&rct=j&q=&esrc=s&source=images&cd=&ved=2ahUKEwjR-82Lo7DlAhVdAxAIHfzyBkUQjRx6BAgBEAQ&url=https%3A%2F%2Finkdaze.com%2Fproducts%2Fsmile&psig=AOvVaw07DhzTK46VHe1ahh__xD9c&ust=1571847673863433","storage":"3","varName":"image","name":"Create Image"},{"storage":"3","varName":"image","effect":"7","name":"Apply Image Effect"},{"storage":"3","varName":"image","channel":"4","varName2":"","message":"","name":"Send Image"}]}]